hazetunnel/__init__.py
hazetunnel/__main__.py
hazetunnel/__version__.py
hazetunnel/bin/__init__.py
hazetunnel/cffi.py
hazetunnel/control.py
hazetunnel-2.0.1.dist-info/entry_points.txt
hazetunnel-2.0.1.dist-info/METADATA
hazetunnel-2.0.1.dist-info/WHEEL
hazetunnel-2.0.1.dist-info/RECORD
